vecquery_tune/__init__.py
vecquery_tune/create_database.py
vecquery_tune/custom_embedding.py
vecquery_tune/fine_tune.py
vecquery_tune/inference.py
vecquery_tune/loss_funcs.py
vecquery_tune/model.py
vecquery_tune/vecquery_tune.py
BERTune-0.0.1.dist-info/LICENSE
BERTune-0.0.1.dist-info/METADATA
BERTune-0.0.1.dist-info/WHEEL
BERTune-0.0.1.dist-info/top_level.txt
BERTune-0.0.1.dist-info/RECORD
